all2graph-0.4.4.dist-info/top_level.txt
all2graph-0.4.4.dist-info/WHEEL
all2graph-0.4.4.dist-info/METADATA
all2graph-0.4.4.dist-info/RECORD
all2graph-0.4.4.dist-info/LICENSE
all2graph/meta_struct.py
all2graph/globals.py
all2graph/meta_struct.cpython-37m-x86_64-linux-gnu.so
all2graph/__init__.py
all2graph/version.py
all2graph/info/graph_info.py
all2graph/info/str_info.py
all2graph/info/meta_info_test.py
all2graph/info/meta_info.py
all2graph/info/node_info.py
all2graph/info/edge_info.py
all2graph/info/graph_info_test.py
all2graph/info/__init__.py
all2graph/stats/ecdf_test.py
all2graph/stats/distribution.py
all2graph/stats/__init__.py
all2graph/stats/ecdf.py
all2graph/stats/discrete.py
all2graph/stats/discrete_test.py
all2graph/graph/graph.py
all2graph/graph/graph_test.py
all2graph/graph/raw_graph.cpython-37m-x86_64-linux-gnu.so
all2graph/graph/raw_graph_test.py
all2graph/graph/__init__.py
all2graph/graph/raw_graph.py
all2graph/parsers/graph_parser.cpython-37m-x86_64-linux-gnu.so
all2graph/parsers/data_parser.py
all2graph/parsers/graph_parser_test.py
all2graph/parsers/parser_wrapper.cpython-37m-x86_64-linux-gnu.so
all2graph/parsers/json_parser_test.py
all2graph/parsers/graph_parser.py
all2graph/parsers/data_parser.cpython-37m-x86_64-linux-gnu.so
all2graph/parsers/__init__.py
all2graph/parsers/parser_wrapper.py
all2graph/parsers/json_parser.py
all2graph/parsers/json_parser.cpython-37m-x86_64-linux-gnu.so
all2graph/parsers/parser_wrapper_test.py
all2graph/nn/framework_test.py
all2graph/nn/embedding.py
all2graph/nn/utils.py
all2graph/nn/body.py
all2graph/nn/feedforward.py
all2graph/nn/bottle_neck.py
all2graph/nn/head.py
all2graph/nn/body_test.py
all2graph/nn/framework.py
all2graph/nn/__init__.py
all2graph/nn/loss.py
all2graph/nn/train/early_stop.py
all2graph/nn/train/hyperband.py
all2graph/nn/train/callback.py
all2graph/nn/train/history.py
all2graph/nn/train/trainer_test.py
all2graph/nn/train/trainer.py
all2graph/nn/train/metric.py
all2graph/nn/train/__init__.py
all2graph/nn/models/model.py
all2graph/nn/models/gatfm_test.py
all2graph/nn/models/__init__.py
