Metadata-Version: 2.1
Name: all2graph
Version: 0.4.4
Summary: UNKNOWN
Home-page: https://github.com/wolaituodiban/all2graph.git
Author: xiaotian chen
Author-email: wolaituodiban@gmail.com
License: MIT
Platform: UNKNOWN
Classifier: Programming Language :: Python :: 3
Classifier: Operating System :: OS Independent
License-File: LICENSE
Requires-Dist: numpy
Requires-Dist: pandas
Requires-Dist: scipy
Requires-Dist: tqdm
